pinch/__init__.py
pinch/audio.py
pinch/client.py
pinch/config.py
pinch/errors.py
pinch/events.py
pinch/file_translate.py
pinch/py.typed
pinch/session.py
pinch/stream.py
pinch_sdk-0.1.1.dist-info/METADATA
pinch_sdk-0.1.1.dist-info/WHEEL
pinch_sdk-0.1.1.dist-info/licenses/LICENSE
pinch_sdk-0.1.1.dist-info/RECORD
