Metadata-Version: 2.4
Name: pinch-sdk
Version: 0.1.1
Summary: Pinch Python SDK for real-time speech translation
Project-URL: Homepage, https://startpinch.com
Project-URL: Repository, https://github.com/pinch-eng/pinch-python-sdk
Project-URL: Documentation, https://github.com/pinch-eng/pinch-python-sdk#readme
Author: Pinch
License: MIT
License-File: LICENSE
Keywords: audio,pinch,realtime,speech,stt,translation,tts,voice
Classifier: Development Status :: 4 - Beta
Classifier: Intended Audience :: Developers
Classifier: License :: OSI Approved :: MIT License
Classifier: Programming Language :: Python :: 3
Classifier: Programming Language :: Python :: 3.10
Classifier: Programming Language :: Python :: 3.11
Classifier: Programming Language :: Python :: 3.12
Classifier: Typing :: Typed
Requires-Python: >=3.10
Requires-Dist: httpx>=0.25.0
Requires-Dist: livekit>=0.12.0
Provides-Extra: audio
Requires-Dist: numpy>=1.24.0; extra == 'audio'
Requires-Dist: soxr>=0.3.7; extra == 'audio'
Provides-Extra: dev
Requires-Dist: pytest>=8.0.0; extra == 'dev'
